setup.cfg
setup.py
pyfreeling/__init__.py
pyfreeling.egg-info/PKG-INFO
pyfreeling.egg-info/SOURCES.txt
pyfreeling.egg-info/dependency_links.txt
pyfreeling.egg-info/requires.txt
pyfreeling.egg-info/top_level.txt
pyfreeling/tests/__init__.py
pyfreeling/tests/test_analyze.py